algorithms/__init__.py
algorithms/socialprograms.py
socialprograms-0.4.0.dist-info/METADATA
socialprograms-0.4.0.dist-info/WHEEL
socialprograms-0.4.0.dist-info/top_level.txt
socialprograms-0.4.0.dist-info/RECORD
