Metadata-Version: 2.1
Name: socialprograms
Version: 0.4.0
Summary: A package to evaluate social programs
Home-page: https://github.com/SESNA-Inteligencia/Algoritmos
Author: dgria-inteligencia
Author-email: sesna.dgria.inteligencia@gmail.com
Requires-Python: >= 3.10.0
Requires-Dist: pandas (>=1.0.0)
Requires-Dist: numpy (>=1.15.0)
